armstrong/__init__.py
abhiarmstrongseries-0.0.1.dist-info/LICENCE.txt
abhiarmstrongseries-0.0.1.dist-info/METADATA
abhiarmstrongseries-0.0.1.dist-info/WHEEL
abhiarmstrongseries-0.0.1.dist-info/top_level.txt
abhiarmstrongseries-0.0.1.dist-info/RECORD
