Metadata-Version: 2.1
Name: abhiarmstrongseries
Version: 0.0.1
Summary: it checks and prints armstrong numbers
Home-page: 
Author: Abhijith Krishna G
Author-email: abhijithkrishnag234@gmail.com
License: MIT
Keywords: armstrong,strong,printarmstrong
Classifier: Development Status :: 5 - Production/Stable
Classifier: Intended Audience :: Education
Classifier: Operating System :: Microsoft :: Windows
Classifier: License :: OSI Approved :: MIT License
Classifier: Programming Language :: Python :: 3
License-File: LICENCE.txt
